README.md
cpg-create
cpg-query
cpg-version
setup.py
cpgclient/CpgClient.py
cpgclient/__init__.py
cpgclientlib.egg-info/PKG-INFO
cpgclientlib.egg-info/SOURCES.txt
cpgclientlib.egg-info/dependency_links.txt
cpgclientlib.egg-info/requires.txt
cpgclientlib.egg-info/top_level.txt