Metadata-Version: 2.1
Name: cpgclientlib
Version: 0.11.55
Summary: A client library for CPG servers
Home-page: https://github.com/ShiftLeftSecurity/codepropertygraph
Author: Fabian Yamaguchi
Author-email: fabs@shiftleft.io
License: UNKNOWN
Platform: UNKNOWN
Classifier: Programming Language :: Python :: 3
Classifier: License :: OSI Approved :: Apache Software License
Classifier: Operating System :: OS Independent
